adafruit_circuitpython_pn532-2.4.7.dist-info/licenses/LICENSE
adafruit_pn532/__init__.py
adafruit_pn532/adafruit_pn532.py
adafruit_pn532/i2c.py
adafruit_pn532/spi.py
adafruit_pn532/uart.py
adafruit_circuitpython_pn532-2.4.7.dist-info/METADATA
adafruit_circuitpython_pn532-2.4.7.dist-info/WHEEL
adafruit_circuitpython_pn532-2.4.7.dist-info/top_level.txt
adafruit_circuitpython_pn532-2.4.7.dist-info/RECORD
