Metadata-Version: 2.4
Name: adafruit-circuitpython-pn532
Version: 2.4.7
Summary: CircuitPython library for controlling PN532 RFID/NFC reader-writer.
Author-email: Adafruit Industries <circuitpython@adafruit.com>
License: MIT
Project-URL: Homepage, https://github.com/adafruit/Adafruit_CircuitPython_PN532
Keywords: adafruit,pn532,rfid,nfc,hardware,micropython,circuitpython
Classifier: Intended Audience :: Developers
Classifier: Topic :: Software Development :: Libraries
Classifier: Topic :: Software Development :: Embedded Systems
Classifier: Topic :: System :: Hardware
Classifier: License :: OSI Approved :: MIT License
Classifier: Programming Language :: Python :: 3
License-File: LICENSE
Requires-Dist: Adafruit-Blinka
Requires-Dist: adafruit-circuitpython-busdevice
Requires-Dist: adafruit-circuitpython-typing
Requires-Dist: pyserial
Requires-Dist: typing-extensions~=4.0
Provides-Extra: optional
Dynamic: license-file
